bclearer_interop_services/__init__.py
bclearer_interop_services/b_dictionary_service/__init__.py
bclearer_interop_services/b_dictionary_service/common_knowledge/__init__.py
bclearer_interop_services/b_dictionary_service/common_knowledge/b_dictionary_return_types.py
bclearer_interop_services/b_dictionary_service/common_knowledge/table_b_dictionary_return_types.py
bclearer_interop_services/b_dictionary_service/common_knowledge/table_register_b_dictionary_return_types.py
bclearer_interop_services/b_dictionary_service/mapper_objects_service/__init__.py
bclearer_interop_services/b_dictionary_service/mapper_objects_service/mapper_objects_to_table_converter.py
bclearer_interop_services/b_dictionary_service/objects/__init__.py
bclearer_interop_services/b_dictionary_service/objects/b_dictionaries.py
bclearer_interop_services/b_dictionary_service/objects/row_b_dictionaries.py
bclearer_interop_services/b_dictionary_service/objects/table_b_dictionaries.py
bclearer_interop_services/b_dictionary_service/objects/table_registers.py
bclearer_interop_services/b_dictionary_service/python_extension_services/__init__.py
bclearer_interop_services/b_dictionary_service/python_extension_services/dictionary_joiner.py
bclearer_interop_services/b_dictionary_service/table_as_dictionary_service/__init__.py
bclearer_interop_services/b_dictionary_service/table_as_dictionary_service/data_policy_carriage_return_to_table_as_dictionary_applicator.py
bclearer_interop_services/b_dictionary_service/table_as_dictionary_service/dataframe_to_table_as_dictionary_converter.py
bclearer_interop_services/b_dictionary_service/table_as_dictionary_service/static_column_value_to_table_as_dictionary_adder.py
bclearer_interop_services/b_dictionary_service/table_as_dictionary_service/table_as_dictionary_by_column_value_filter.py
bclearer_interop_services/b_dictionary_service/table_as_dictionary_service/table_as_dictionary_by_column_value_not_matching_filterer.py
ontledgy_bclearer_interop_services-0.1.0.dist-info/METADATA
ontledgy_bclearer_interop_services-0.1.0.dist-info/WHEEL
ontledgy_bclearer_interop_services-0.1.0.dist-info/RECORD
