Metadata-Version: 2.1
Name: ontledgy-bclearer-interop-services
Version: 0.1.0
Summary: "A set of interop services to integrate and transfer data between different applications, model and storage technologies for the bclearer framework."
Author: Mesbah Khan
Author-email: khanm@ontoledgy.io
Requires-Python: >=3.12,<4.0
Classifier: Programming Language :: Python :: 3
Classifier: Programming Language :: Python :: 3.12
Requires-Dist: ontoledgy-bclearer-orchestration-services (>=0.1.0,<0.2.0)
